topsis/Topsis.py
topsis/Topsis_driver.py
Topsis_akashjindal347-0.0.1.dist-info/LICENSE
Topsis_akashjindal347-0.0.1.dist-info/METADATA
Topsis_akashjindal347-0.0.1.dist-info/WHEEL
Topsis_akashjindal347-0.0.1.dist-info/top_level.txt
Topsis_akashjindal347-0.0.1.dist-info/RECORD
